fcp_common/__init__.py
fcp_common/public/__init__.py
fcp_common/public/error_codes.py
rhino_health/__init__.py
rhino_health/lib/__init__.py
rhino_health/lib/constants.py
rhino_health/lib/dataclass.py
rhino_health/lib/rest_handler.py
rhino_health/lib/rhino_client.py
rhino_health/lib/rhino_cloud.py
rhino_health/lib/rhino_session.py
rhino_health/lib/utils.py
rhino_health/lib/endpoints/__init__.py
rhino_health/lib/endpoints/endpoint.py
rhino_health/lib/endpoints/code_object/__init__.py
rhino_health/lib/endpoints/code_object/code_object_dataclass.py
rhino_health/lib/endpoints/code_object/code_object_endpoints.py
rhino_health/lib/endpoints/code_run/__init__.py
rhino_health/lib/endpoints/code_run/code_run_dataclass.py
rhino_health/lib/endpoints/code_run/code_run_endpoints.py
rhino_health/lib/endpoints/data_schema/__init__.py
rhino_health/lib/endpoints/data_schema/data_schema_dataclass.py
rhino_health/lib/endpoints/data_schema/data_schema_endpoints.py
rhino_health/lib/endpoints/dataset/__init__.py
rhino_health/lib/endpoints/dataset/dataset_dataclass.py
rhino_health/lib/endpoints/dataset/dataset_endpoints.py
rhino_health/lib/endpoints/dicomweb_query/__init__.py
rhino_health/lib/endpoints/dicomweb_query/dicomweb_query_dataclass.py
rhino_health/lib/endpoints/dicomweb_query/dicomweb_query_endpoints.py
rhino_health/lib/endpoints/federated_dataset/__init__.py
rhino_health/lib/endpoints/federated_dataset/federated_dataset_dataclass.py
rhino_health/lib/endpoints/federated_dataset/federated_dataset_endpoints.py
rhino_health/lib/endpoints/project/__init__.py
rhino_health/lib/endpoints/project/project_baseclass.py
rhino_health/lib/endpoints/project/project_dataclass.py
rhino_health/lib/endpoints/project/project_endpoints.py
rhino_health/lib/endpoints/runtime_file/__init__.py
rhino_health/lib/endpoints/runtime_file/runtime_file_dataclass.py
rhino_health/lib/endpoints/runtime_file/runtime_file_endpoints.py
rhino_health/lib/endpoints/semantic_mapping/__init__.py
rhino_health-2.1.15.dist-info/METADATA
rhino_health-2.1.15.dist-info/WHEEL
rhino_health-2.1.15.dist-info/licenses/LICENSE.md
rhino_health-2.1.15.dist-info/RECORD
