Metadata-Version: 2.4
Name: rhino_health
Version: 2.1.15
Summary: Standard Development Kit for interacting with the Rhino Health Federated Learning Platform
Project-URL: Homepage, https://www.rhinohealth.com/
Project-URL: Documentation, https://rhinohealth.github.io/rhino_sdk_docs/html/index.html
Author-email: Rhino Health <rhino-sdk@rhinohealth.com>
Maintainer-email: Rhino Health <rhino-sdk@rhinohealth.com>
License: ## RHINO HEALTH PYTHON SDK LICENSE AGREEMENT
License-File: LICENSE.md
Keywords: AI,Federated,Federated Learning,Rhino,Rhino Health,SDK
Classifier: Development Status :: 3 - Alpha
Classifier: Intended Audience :: Developers
Classifier: Intended Audience :: Healthcare Industry
Classifier: Intended Audience :: Science/Research
Classifier: License :: Other/Proprietary License
Classifier: Natural Language :: English
Classifier: Operating System :: OS Independent
Classifier: Programming Language :: Python
Classifier: Programming Language :: Python :: 3.9
Classifier: Programming Language :: Python :: 3.10
Classifier: Programming Language :: Python :: 3.11
Classifier: Programming Language :: Python :: 3.12
Classifier: Programming Language :: Python :: 3.13
Classifier: Programming Language :: Python :: 3.14
Classifier: Topic :: Scientific/Engineering
Classifier: Topic :: Software Development :: Libraries
Requires-Python: >=3.9
Requires-Dist: arrow<2.0,>=1.2.1
Requires-Dist: backoff<3.0,>=2.1.1
Requires-Dist: funcy<3.0,>=1.16
Requires-Dist: pydantic<3.0,>=2.5
Requires-Dist: ratelimit<3.0,>=2.2.1
Requires-Dist: requests<3.0,>=2.28
Requires-Dist: typing-extensions<5.0,>=4.8.0
Provides-Extra: dev
Requires-Dist: hatch<2,>=1.16; extra == 'dev'
Requires-Dist: myst-parser<3,>=2; extra == 'dev'
Requires-Dist: numpydoc<1.7,>=1.6.0; extra == 'dev'
Requires-Dist: pydata-sphinx-theme<0.15.3,>=0.14.4; extra == 'dev'
Requires-Dist: sphinx-autoapi<3.1,>=3.0; extra == 'dev'
Requires-Dist: sphinx-sitemap<2.6,>=2.5; extra == 'dev'
Requires-Dist: sphinx<8,>=7; extra == 'dev'
Provides-Extra: kaplan-meier
Requires-Dist: statsmodels<0.15,>=0.12.0; extra == 'kaplan-meier'
Provides-Extra: lint
Requires-Dist: black~=23.1.0; extra == 'lint'
Requires-Dist: isort; extra == 'lint'
Requires-Dist: pylint; extra == 'lint'
Provides-Extra: test
Requires-Dist: coverage<=8,>7; extra == 'test'
Requires-Dist: factory-boy<3.3,>=3.2.1; extra == 'test'
Requires-Dist: pytest>=6.0.0; extra == 'test'
Requires-Dist: responses<0.25,>=0.23.1; extra == 'test'
Requires-Dist: tox<5,>=4; extra == 'test'
